README.rst
setup.cfg
setup.py
/Users/bustawin/Documents/repos/bigsheet/bigsheets/domain/__pycache__/__init__.cpython-37.pyc
/Users/bustawin/Documents/repos/bigsheet/bigsheets/domain/__pycache__/command.cpython-37.pyc
/Users/bustawin/Documents/repos/bigsheet/bigsheets/domain/__pycache__/event.cpython-37.pyc
BigSheets.egg-info/PKG-INFO
BigSheets.egg-info/SOURCES.txt
BigSheets.egg-info/dependency_links.txt
BigSheets.egg-info/requires.txt
BigSheets.egg-info/top_level.txt
bigsheets/__init__.py
bigsheets/app.py
bigsheets/main.py
bigsheets/adapters/__init__.py
bigsheets/adapters/container.py
bigsheets/adapters/errors/__init__.py
bigsheets/adapters/errors/errors.py
bigsheets/adapters/sheets/__init__.py
bigsheets/adapters/sheets/file.py
bigsheets/adapters/sheets/sheets.py
bigsheets/adapters/ui/__init__.py
bigsheets/adapters/ui/ui_port.py
bigsheets/adapters/ui/gui/__init__.py
bigsheets/adapters/ui/gui/gui.py
bigsheets/adapters/ui/gui/utils.py
bigsheets/adapters/ui/gui/query/__init__.py
bigsheets/adapters/ui/gui/query/controller.py
bigsheets/adapters/ui/gui/query/query_window.py
bigsheets/adapters/ui/gui/query/view.py
bigsheets/adapters/ui/gui/warnings/__init__.py
bigsheets/adapters/ui/gui/warnings/view.py
bigsheets/adapters/ui/gui/warnings/warnings_window.py
bigsheets/domain/__init__.py
bigsheets/domain/command.py
bigsheets/domain/error.py
bigsheets/domain/event.py
bigsheets/domain/sheet.py
bigsheets/service/__init__.py
bigsheets/service/command_handlers.py
bigsheets/service/event_handlers.py
bigsheets/service/handler.py
bigsheets/service/message_bus.py
bigsheets/service/read_model.py
bigsheets/service/running.py
bigsheets/service/unit_of_work.py
bigsheets/service/utils.py
test/__init__.py
test/conftest.py
test/e2e/__init__.py
test/e2e/test_use_cases.py