Metadata-Version: 2.1
Name: BigSheets
Version: 1.0b1
Summary: Sheets
Home-page: https://github.com/bustawin/bigsheets
Author: Xavier Bustamante
Author-email: xavier@bustawin.com
License: Private
Project-URL: Documentation, https://github.com/bustawin/bigsheets
Project-URL: Code, https://github.com/bustawin/bigsheets
Project-URL: Issue tracker, https://github.com/bustawin/bigsheets/issues/
Platform: UNKNOWN
Classifier: Development Status :: 2 - Pre-Alpha
Classifier: Operating System :: OS Independent
Classifier: Programming Language :: Python :: 3 :: Only
Classifier: Programming Language :: Python :: 3.8
Requires-Python: >=3.8
Provides-Extra: build
Provides-Extra: test
Provides-Extra: coverage
